NetkillerManagement/README.md
NetkillerManagement/__init__.py
NetkillerManagement/__main__.py
NetkillerManagement/file.epub
NetkillerManagement/index.html
NetkillerManagement/css/__init__.py
NetkillerManagement/css/annotations.css
NetkillerManagement/css/main.css
NetkillerManagement/css/normalize.css
NetkillerManagement/css/popup.css
NetkillerManagement/font/__init__.py
NetkillerManagement/font/fontello.eot
NetkillerManagement/font/fontello.svg
NetkillerManagement/font/fontello.ttf
NetkillerManagement/font/fontello.woff
NetkillerManagement/img/__init__.py
NetkillerManagement/img/annotator-glyph-sprite.png
NetkillerManagement/img/annotator-icon-sprite.png
NetkillerManagement/img/apple-touch-icon.png
NetkillerManagement/img/cancelfullscreen.png
NetkillerManagement/img/close.png
NetkillerManagement/img/fullscreen.png
NetkillerManagement/img/loader.gif
NetkillerManagement/img/menu-icon.png
NetkillerManagement/img/save.png
NetkillerManagement/img/saved.png
NetkillerManagement/img/settings-s.png
NetkillerManagement/img/settings.png
NetkillerManagement/img/star.png
NetkillerManagement/js/__init__.py
NetkillerManagement/js/epub.js
NetkillerManagement/js/epub.min.js
NetkillerManagement/js/epub.min.map
NetkillerManagement/js/hooks.min.js
NetkillerManagement/js/hooks.min.map
NetkillerManagement/js/reader.js
NetkillerManagement/js/reader.js.map
NetkillerManagement/js/reader.min.js
NetkillerManagement/js/reader.min.map
NetkillerManagement/js/hooks/__init__.py
NetkillerManagement/js/hooks/extensions/__init__.py
NetkillerManagement/js/hooks/extensions/highlight.js
NetkillerManagement/js/libs/__init__.py
NetkillerManagement/js/libs/jquery.min.js
NetkillerManagement/js/libs/localforage.min.js
NetkillerManagement/js/libs/screenfull.js
NetkillerManagement/js/libs/screenfull.min.js
NetkillerManagement/js/libs/zip.min.js
NetkillerManagement/js/plugins/__init__.py
NetkillerManagement/js/plugins/hypothesis.js
NetkillerManagement/js/plugins/search.js
netkiller_management-2024.3.5.0.dist-info/METADATA
netkiller_management-2024.3.5.0.dist-info/WHEEL
netkiller_management-2024.3.5.0.dist-info/entry_points.txt
netkiller_management-2024.3.5.0.dist-info/top_level.txt
netkiller_management-2024.3.5.0.dist-info/RECORD
